adaptive_resampling/__init__.py
adaptive_resampling/border_detection.py
adaptive_resampling-0.1.1.dist-info/LICENSE
adaptive_resampling-0.1.1.dist-info/METADATA
adaptive_resampling-0.1.1.dist-info/WHEEL
adaptive_resampling-0.1.1.dist-info/top_level.txt
adaptive_resampling-0.1.1.dist-info/RECORD
