Metadata-Version: 2.1
Name: adaptive-resampling
Version: 0.1.1
Summary: A package for adaptive resampling of datasets using border detection.
Home-page: https://github.com/ykahalan/adaptive_resampling
Author: Yunis Kahalan
Author-email: ykahalan@gmail.com
Classifier: Programming Language :: Python :: 3
Classifier: License :: OSI Approved :: MIT License
Classifier: Operating System :: OS Independent
Requires-Python: >=3.6
License-File: LICENSE
Requires-Dist: numpy
Requires-Dist: scikit-learn
